{
  "lastUpdated": "2026-04-19T17:04:33.690Z",
  "overview": {
    "totalLaunched": 68624,
    "payloads": 25872,
    "inOrbit": 33604,
    "decayed": 35020,
    "launchFailures": 521,
    "partialFailures": 34
  },
  "payloads": {
    "total": 25872,
    "inOrbit": 18605,
    "decayed": 7267,
    "active": 15588
  },
  "starlink": {
    "total": 11697,
    "inOrbit": 10176,
    "decayed": 1521,
    "active": 10170,
    "launchFailures": 1
  },
  "rocketBodies": {
    "total": 6835,
    "inOrbit": 2398,
    "decayed": 4437,
    "active": 0
  },
  "debris": {
    "total": 35751,
    "inOrbit": 12540,
    "decayed": 23211,
    "active": 0
  },
  "unknown": {
    "total": 166,
    "inOrbit": 61,
    "decayed": 105,
    "active": 0
  }
}
