{
  "lastUpdated": "2026-05-16T11:36:19.285Z",
  "overview": {
    "totalLaunched": 68992,
    "payloads": 26241,
    "inOrbit": 33864,
    "decayed": 35128,
    "launchFailures": 522,
    "partialFailures": 34
  },
  "payloads": {
    "total": 26241,
    "inOrbit": 18895,
    "decayed": 7346,
    "active": 15878
  },
  "starlink": {
    "total": 11927,
    "inOrbit": 10370,
    "decayed": 1557,
    "active": 10364,
    "launchFailures": 1
  },
  "rocketBodies": {
    "total": 6841,
    "inOrbit": 2401,
    "decayed": 4440,
    "active": 1
  },
  "debris": {
    "total": 35754,
    "inOrbit": 12518,
    "decayed": 23236,
    "active": 0
  },
  "unknown": {
    "total": 156,
    "inOrbit": 50,
    "decayed": 106,
    "active": 0
  }
}
