{
  "lastUpdated": "2026-05-15T21:33:25.513Z",
  "overview": {
    "totalLaunched": 68992,
    "payloads": 26240,
    "inOrbit": 33865,
    "decayed": 35127,
    "launchFailures": 522,
    "partialFailures": 34
  },
  "payloads": {
    "total": 26240,
    "inOrbit": 18894,
    "decayed": 7346,
    "active": 15877
  },
  "starlink": {
    "total": 11927,
    "inOrbit": 10370,
    "decayed": 1557,
    "active": 10364,
    "launchFailures": 1
  },
  "rocketBodies": {
    "total": 6840,
    "inOrbit": 2400,
    "decayed": 4440,
    "active": 1
  },
  "debris": {
    "total": 35754,
    "inOrbit": 12519,
    "decayed": 23235,
    "active": 0
  },
  "unknown": {
    "total": 158,
    "inOrbit": 52,
    "decayed": 106,
    "active": 0
  }
}
